meritous/core/__init__.py
meritous/core/exceptions.py
meritous/core/i18n.py
meritous/core/properties.py
meritous/core/serializers.py
meritous/core/stores.py
meritous/core/i18n_data/en.toml
meritous-1.2.2.dist-info/LICENSE
meritous-1.2.2.dist-info/WHEEL
meritous-1.2.2.dist-info/METADATA
meritous-1.2.2.dist-info/RECORD
