Metadata-Version: 2.1
Name: meritous
Version: 1.2.2
Summary: Simple Python Models
Keywords: model
Author-email: Tom Morton <tom@errant.me.uk>
Requires-Python: >=3.10
Classifier: License :: OSI Approved :: MIT License
Classifier: Development Status :: 4 - Beta
Classifier: Programming Language :: Python :: 3
Classifier: Programming Language :: Python :: 3 :: Only
Classifier: Programming Language :: Python :: 3.10
Classifier: Programming Language :: Python :: 3.11
Classifier: Programming Language :: Python :: 3.12
Requires-Dist: toml
Requires-Dist: dotmap
Requires-Dist: sphinx ; extra == "doc"
Requires-Dist: sphinx-rtd-theme ; extra == "doc"
Requires-Dist: pytest >=5.3.2 ; extra == "test"
Requires-Dist: pytest-cov ; extra == "test"
Project-URL: GitHub, https://github.com/errant/meritous/
Project-URL: Home, https://meritous.readthedocs.io/en/latest/
Provides-Extra: doc
Provides-Extra: test
